setup.py
pyxml2obj/__init__.py
pyxml2obj/pyxml2obj.py
pyxml2obj/pyxml2obj_in_test.py
pyxml2obj/pyxml2obj_out_test.py
pyxml2obj.egg-info/PKG-INFO
pyxml2obj.egg-info/SOURCES.txt
pyxml2obj.egg-info/dependency_links.txt
pyxml2obj.egg-info/top_level.txt
