Metadata-Version: 1.0
Name: pyxml2obj
Version: 0.1.2.9
Summary: pyxml2obj convert xml to python object and vice versa. This module is inspired by XML::Simple in CPAN
Home-page: http://github.com/taichino/pyxml2obj
Author: Matsumoto Taichi (taichino@gmail.com)
Author-email: taichino@gmail.com
License: MIT License
Keywords: xml,xml converter,xml to object
Platform: UNKNOWN
Classifier: Development Status :: 3 - Alpha
Classifier: Intended Audience :: Developers
Classifier: License :: OSI Approved :: MIT License
Classifier: Operating System :: POSIX
Classifier: Programming Language :: Python
Classifier: Topic :: Software Development :: Libraries :: Python Modules
